Workbook

Sheet Read Me
A1: The Fourth Estate (variant) -- card content
A2: Exported from docs/deck-dc.csv, docs/elections-dc.csv and docs/papers-dc.csv on the variant branch.
A3: Those CSV files are what the game reads; this workbook is a copy. Influence and prestige are split into readable columns here;
A4: every other column keeps its CSV name, and the key column identifies each card, so edited rows can be imported back.
A6: Sheets
A7: Stories -- every card kind: stories, media events, starters (Letter, Local Notice), Editorial, Scandal.
A8: Elections -- the 17 election cards: two candidates each, thresholds, the card's power and its First Appearance event.
A9: Newspapers -- the eight papers (DC's Super Heroes) and their abilities.
A10: Summary -- counts by type, theme and era, as formulas over the Stories sheet.
A12: Stories columns
A13: cost = price on the exchange; Prestige = the score; Influence (plain) = spends on anything;
A14: Political / Economic / Social influence = influence of that theme (a story has at most one); Campaign influence = elections only;
... A29: scandal, scandal_leader, unscandal, sweep; fa_n = how many.

Sheet Stories
A1: key | B1: name | C1: type | D1: theme | E1: cost | F1: Prestige | G1: Influence (plain) | H1: Political influence | I1: Economic influence | J1: Social influence | K1: Campaign influence | L1: draw | M1: trash | N1: gain_upto | O1: chain | P1: per_same | Q1: per_office | R1: attack | S1: defense | T1: retract | U1: ongoing_gen | V1: ongoing_draw | W1: others_bonus | X1: others_theme | Y1: released | Z1: year | AA1: copies | AB1: card_text | AC1: flavor
A2: letter | B2: Letter to the Editor | C2: Starter | E2: 0 | F2: 0 | G2: 1 | H2: 0 | I2: 0 | J2: 0 | K2: 0 | L2: 0 | M2: 0 | N2: 0 | O2: 0 | P2: 0 | Q2: 0 | S2: 0 | T2: 0 | U2: 0 | V2: 0 | W2: 0 | AA2: 7 | AB2: +1 influence. | AC2: A subscriber's opinion, printed at no charge.
A3: notice | B3: Local Notice | C3: Starter | E3: 0 | F3: 0 | G3: 0 | H3: 0 | I3: 0 | J3: 0 | K3: 0 | L3: 0 | M3: 0 | N3: 0 | O3: 0 | P3: 0 | Q3: 0 | S3: 0 | T3: 0 | U3: 0 | V3: 0 | W3: 0 | AA3: 3 | AB3: No effect. Destroy it when you can. | AC3: Strayed cattle, a church supper. Fills the column; moves no one.
A4: editorial | B4: Editorial | C4: Editorial | E4: 3 | F4: 1 | G4: 2 | H4: 0 | I4: 0 | J4: 0 | K4: 0 | L4: 0 | M4: 0 | N4: 0 | O4: 0 | P4: 0 | Q4: 0 | S4: 0 | T4: 0 | U4: 0 | V4: 0 | W4: 0 | AA4: 16 | AB4: +2 influence. | AC4: The editor's own voice, always on offer.
A5: scandal | B5: Scandal | C5: Scandal | E5: 0 | F5: -1 | G5: 0 | H5: 0 | I5: 0 | J5: 0 | K5: 0 | L5: 0 | M5: 0 | N5: 0 | O5: 0 | P5: 0 | Q5: 0 | S5: 0 | T5: 0 | U5: 0 | V5: 0 | W5: 0 | AA5: 20 | AB5: -1 prestige at the end of the game. | AC5: Something printed about you. It will not go away.
A6: stamp_act | B6: The Stamp Act | C6: Negative story | D6: Economic | E6: 3 | F6: 0 | G6: 1 | H6: 0 | I6: 1 | J6: 0 | K6: 0 | L6: 0 | M6: 0 | N6: 0 | O6: 0 | P6: 0 | Q6: 0 | R6: discard | S6: 0 | T6: 0 | U6: 0 | V6: 0 | W6: 0 | Y6: 1796 | Z6: 1765 | AA6: 1 | AB6: +1 influence, +1 Economic. Attack: each rival paper discards a card at random; +1 influence if it hits any of them. Worth no prestige. | AC6: A tax on every sheet a printer used. The printers led the resistance, and never forgot who had tried to tax the press.
A7: boston_massacre | B7: The Boston Massacre | C7: Negative story | D7: Social | E7: 4 | F7: 0 | G7: 1 | H7: 0 | I7: 0 | J7: 1 | K7: 0 | L7: 0 | M7: 0 | N7: 0 | O7: 0 | P7: 0 | Q7: 0 | R7: scandal | S7: 0 | T7: 0 | U7: 0 | V7: 0 | W7: 0 | Y7: 1796 | Z7: 1770 | AA7: 1 | AB7: +1 influence, +1 Social. Attack: each rival paper gains a Scandal; +1 influence if it hits any of them. Worth no prestige. | AC7: Five dead on King Street. Revere's engraving of it outsold anything true.
A8: tea_party | B8: The Boston Tea Party | C8: Economic story | D8: Economic | E8: 4 | F8: 1 | G8: 2 | H8: 0 | I8: 1 | J8: 0 | K8: 0 | L8: 0 | M8: 0 | N8: 0 | O8: 0 | P8: 1 | Q8: 0 | S8: 0 | T8: 0 | U8: 0 | V8: 0 | W8: 0 | Y8: 1796 | Z8: 1773 | AA8: 1 | AB8: +2 influence, +1 Economic. +1 influence for each other Economic story you play this turn. | AC8: Three shiploads of East India tea in the harbour, and a question about who governs a colony.
A9: common_sense | B9: Common Sense | C9: Social story | D9: Social | E9: 6 | F9: 2 | G9: 0 | H9: 0 | I9: 0 | J9: 2 | K9: 0 | L9: 1 | M9: 0 | N9: 0 | O9: 2 | P9: 0 | Q9: 0 | S9: 1 | T9: 0 | U9: 0 | V9: 0 | W9: 0 | Y9: 1796 | Z9: 1776 | AA9: 1 | AB9: +2 Social, draw 1 card. If you play another Social story this turn, +2 influence. Defense: discard this from your hand to ignore a negative story, and draw a card. | AC9: Paine's pamphlet ran through edition after edition in months. Kings, it turned out, were optional.
A10: declaration | B10: The Declaration of Independence | C10: Political story | D10: Political | E10: 5 | F10: 1 | G10: 2 | H10: 2 | I10: 0 | J10: 0 | K10: 2 | L10: 0 | M10: 0 | N10: 0 | O10: 0 | P10: 0 | Q10: 0 | S10: 0 | T10: 1 | U10: 0 | V10: 0 | W10: 0 | Y10: 1796 | Z10: 1776 | AA10: 1 | AB10: +2 influence, +2 Political, +2 Campaign (elections only). Retraction: draw a card, and you may destroy a Scandal in your hand or discard pile. | AC10: Printed overnight as a broadside and read aloud from courthouse steps. Everyone would claim it.
A11: saratoga | B11: Saratoga | C11: Political story | D11: Political | E11: 5 | F11: 1 | G11: 2 | H11: 2 | I11: 0 | J11: 0 | K11: 2 | L11: 0 | M11: 0 | N11: 0 | O11: 0 | P11: 0 | Q11: 0 | S11: 0 | T11: 1 | U11: 0 | V11: 0 | W11: 0 | Y11: 1796 | Z11: 1777 | AA11: 1 | AB11: +2 influence, +2 Political, +2 Campaign (elections only). Retraction: draw a card, and you may destroy a Scandal in your hand or discard pile. | AC11: Burgoyne surrendered an army, and France decided the rebellion was worth backing.
A12: valley_forge | B12: Valley Forge | C12: Social story | D12: Social | E12: 2 | F12: 1 | G12: 1 | H12: 0 | I12: 0 | J12: 0 | K12: 0 | L12: 1 | M12: 0 | N12: 0 | O12: 0 | P12: 0 | Q12: 0 | S12: 1 | T12: 0 | U12: 0 | V12: 0 | W12: 0 | Y12: 1796 | Z12: 1777 | AA12: 1 | AB12: +1 influence, draw 1 card. Defense: discard this from your hand to ignore a negative story, and draw a card. | AC12: A winter camp starved by a Congress that could ask the states for supplies but not require them.
A13: articles_confederation | B13: The Articles of Confederation | C13: Political story | D13: Political | E13: 2 | F13: 1 | G13: 1 | H13: 2 | I13: 0 | J13: 0 | K13: 0 | L13: 0 | M13: 0 | N13: 0 | O13: 0 | P13: 0 | Q13: 0 | S13: 0 | T13: 0 | U13: 0 | V13: 0 | W13: 0 | Y13: 1796 | Z13: 1781 | AA13: 1 | AB13: +1 influence, +2 Political. | AC13: A league of friendship among sovereign states, with no power to tax and no one to enforce it.
A14: newburgh | B14: The Newburgh Conspiracy | C14: Negative story | D14: Political | E14: 2 | F14: 0 | G14: 1 | H14: 0 | I14: 0 | J14: 0 | K14: 0 | L14: 0 | M14: 0 | N14: 0 | O14: 0 | P14: 0 | Q14: 0 | R14: discard | S14: 0 | T14: 0 | U14: 0 | V14: 0 | W14: 0 | Y14: 1796 | Z14: 1783 | AA14: 1 | AB14: +1 influence. Attack: each rival paper discards a card at random; +1 influence if it hits any of them. Worth no prestige. | AC14: Unpaid officers threatened Congress. Washington fumbled for his spectacles and talked them down.
A15: treaty_of_paris | B15: The Treaty of Paris | C15: Economic story | D15: Economic | E15: 6 | F15: 2 | G15: 2 | H15: 0 | I15: 2 | J15: 0 | K15: 0 | L15: 0 | M15: 0 | N15: 4 | O15: 0 | P15: 1 | Q15: 0 | S15: 0 | T15: 0 | U15: 0 | V15: 0 | W15: 0 | Y15: 1796 | Z15: 1783 | AA15: 1 | AB15: +2 influence, +2 Economic. Gain a story costing 4 or less from the exchange. +1 influence for each other Economic story you play this turn. | AC15: Independence, fisheries and the land to the Mississippi. Peace sells as well as war.
A16: pennsylvania_packet | B16: The First American Daily | C16: Media event | E16: 5 | F16: 1 | G16: 0 | H16: 0 | I16: 0 | J16: 0 | K16: 0 | L16: 0 | M16: 0 | N16: 0 | O16: 0 | P16: 0 | Q16: 0 | S16: 0 | T16: 0 | U16: 1 | V16: 0 | W16: 1 | X16: Economic | Y16: 1796 | Z16: 1784 | AA16: 1 | AB16: Stays in play for the rest of the game. Ongoing: at the start of each of your turns, +1 influence. Every other paper gets +1 Economic influence at the start of each of its turns. | AC16: The Pennsylvania Packet went daily. Advertisers discovered they could reach a city every morning.
A17: shays_rebellion | B17: Shays' Rebellion | C17: Negative story | D17: Economic | E17: 3 | F17: 0 | G17: 1 | H17: 0 | I17: 1 | J17: 0 | K17: 0 | L17: 0 | M17: 0 | N17: 0 | O17: 0 | P17: 0 | Q17: 0 | R17: discard | S17: 0 | T17: 0 | U17: 0 | V17: 0 | W17: 0 | Y17: 1796 | Z17: 1786 | AA17: 1 | AB17: +1 influence, +1 Economic. Attack: each rival paper discards a card at random; +1 influence if it hits any of them. Worth no prestige. | AC17: Farmers closed the courts in western Massachusetts, and the Confederation could do nothing about it.
A18: antifederalist_papers | B18: Brutus and the Federal Farmer | C18: Political story | D18: Political | E18: 3 | F18: 1 | G18: 1 | H18: 2 | I18: 0 | J18: 0 | K18: 1 | L18: 0 | M18: 0 | N18: 0 | O18: 0 | P18: 0 | Q18: 0 | S18: 0 | T18: 1 | U18: 0 | V18: 0 | W18: 0 | Y18: 1796 | Z18: 1787 | AA18: 1 | AB18: +1 influence, +2 Political, +1 Campaign (elections only). Retraction: draw a card, and you may destroy a Scandal in your hand or discard pile. | AC18: The case against ratification: a consolidated government would swallow the states and the liberties with them.
A19: constitutional_convention | B19: The Constitutional Convention | C19: Political story | D19: Political | E19: 3 | F19: 1 | G19: 1 | H19: 2 | I19: 0 | J19: 0 | K19: 1 | L19: 0 | M19: 0 | N19: 0 | O19: 0 | P19: 0 | Q19: 0 | S19: 0 | T19: 1 | U19: 0 | V19: 0 | W19: 0 | Y19: 1796 | Z19: 1787 | AA19: 1 | AB19: +1 influence, +2 Political, +1 Campaign (elections only). Retraction: draw a card, and you may destroy a Scandal in your hand or discard pile. | AC19: Delegates sent to amend the Articles locked the doors in Philadelphia and wrote a new government.
A20: federalist_papers | B20: The Federalist | C20: Political story | D20: Political | E20: 4 | F20: 1 | G20: 1 | H20: 2 | I20: 0 | J20: 0 | K20: 0 | L20: 0 | M20: 0 | N20: 0 | O20: 0 | P20: 0 | Q20: 1 | S20: 0 | T20: 1 | U20: 0 | V20: 0 | W20: 0 | Y20: 1796 | Z20: 1787 | AA20: 1 | AB20: +1 influence, +2 Political. +1 Political for each election you have won. Retraction: draw a card, and you may destroy a Scandal in your hand or discard pile. | AC20: Eighty-five essays by Publius in the New York papers, arguing for a government that could act.
A21: northwest_ordinance | B21: The Northwest Ordinance | C21: Economic story | D21: Economic | E21: 3 | F21: 1 | G21: 1 | H21: 0 | I21: 1 | J21: 0 | K21: 0 | L21: 0 | M21: 1 | N21: 0 | O21: 0 | P21: 1 | Q21: 0 | S21: 0 | T21: 0 | U21: 0 | V21: 0 | W21: 0 | Y21: 1796 | Z21: 1787 | AA21: 1 | AB21: +1 influence, +1 Economic. You may destroy a card in your hand or discard pile. +1 influence for each other Economic story you play this turn. | AC21: Congress would govern the western territories, and no slavery would cross the Ohio.
A22: gazette_of_the_us | B22: The Gazette of the United States | C22: Social story | D22: Social | E22: 4 | F22: 1 | G22: 0 | H22: 0 | I22: 0 | J22: 2 | K22: 0 | L22: 1 | M22: 0 | N22: 0 | O22: 1 | P22: 0 | Q22: 0 | S22: 0 | T22: 0 | U22: 0 | V22: 0 | W22: 0 | Y22: 1796 | Z22: 1789 | AA22: 1 | AB22: +2 Social, draw 1 card. If you play another Social story this turn, +1 influence. | AC22: Fenno's paper followed the government to New York and spoke for Hamilton's Treasury.
A23: judiciary_act | B23: The Judiciary Act | C23: Political story | D23: Political | E23: 2 | F23: 1 | G23: 1 | H23: 2 | I23: 0 | J23: 0 | K23: 0 | L23: 0 | M23: 0 | N23: 0 | O23: 0 | P23: 0 | Q23: 0 | S23: 0 | T23: 0 | U23: 0 | V23: 0 | W23: 0 | Y23: 1796 | Z23: 1789 | AA23: 1 | AB23: +1 influence, +2 Political. | AC23: A Supreme Court, circuit courts and district courts: the federal government acquired a reach.
A24: assumption | B24: The Assumption of State Debts | C24: Economic story | D24: Economic | E24: 4 | F24: 1 | G24: 2 | H24: 0 | I24: 1 | J24: 0 | K24: 0 | L24: 0 | M24: 0 | N24: 0 | O24: 0 | P24: 1 | Q24: 0 | S24: 0 | T24: 0 | U24: 0 | V24: 0 | W24: 0 | Y24: 1796 | Z24: 1790 | AA24: 1 | AB24: +2 influence, +1 Economic. +1 influence for each other Economic story you play this turn. | AC24: The nation took on the war debts of the states, and the speculators who held them grew rich.
A25: residence_act | B25: The Residence Act | C25: Economic story | D25: Economic | E25: 4 | F25: 1 | G25: 2 | H25: 0 | I25: 1 | J25: 0 | K25: 0 | L25: 0 | M25: 0 | N25: 0 | O25: 0 | P25: 1 | Q25: 0 | S25: 0 | T25: 0 | U25: 0 | V25: 0 | W25: 0 | Y25: 1796 | Z25: 1790 | AA25: 1 | AB25: +2 influence, +1 Economic. +1 influence for each other Economic story you play this turn. | AC25: The capital would go to the Potomac, the price the South extracted for assumption.
A26: bank_of_the_us | B26: The Bank of the United States | C26: Economic story | D26: Economic | E26: 5 | F26: 1 | G26: 2 | H26: 0 | I26: 1 | J26: 0 | K26: 0 | L26: 0 | M26: 1 | N26: 0 | O26: 0 | P26: 1 | Q26: 0 | S26: 0 | T26: 0 | U26: 0 | V26: 0 | W26: 0 | Y26: 1796 | Z26: 1791 | AA26: 1 | AB26: +2 influence, +1 Economic. You may destroy a card in your hand or discard pile. +1 influence for each other Economic story you play this turn. | AC26: Hamilton's bank, chartered under powers the Constitution never named. Jefferson called it unconstitutional.
A27: bill_of_rights | B27: The Bill of Rights | C27: Social story | D27: Social | E27: 2 | F27: 1 | G27: 1 | H27: 0 | I27: 0 | J27: 0 | K27: 0 | L27: 1 | M27: 0 | N27: 0 | O27: 0 | P27: 0 | Q27: 0 | S27: 1 | T27: 0 | U27: 0 | V27: 0 | W27: 0 | Y27: 1796 | Z27: 1791 | AA27: 1 | AB27: +1 influence, draw 1 card. Defense: discard this from your hand to ignore a negative story, and draw a card. | AC27: Ten amendments, the first of which said Congress shall make no law abridging the freedom of the press.
A28: national_gazette | B28: The National Gazette | C28: Social story | D28: Social | E28: 4 | F28: 1 | G28: 0 | H28: 0 | I28: 0 | J28: 2 | K28: 0 | L28: 1 | M28: 0 | N28: 0 | O28: 1 | P28: 0 | Q28: 0 | S28: 0 | T28: 0 | U28: 0 | V28: 0 | W28: 0 | Y28: 1796 | Z28: 1791 | AA28: 1 | AB28: +2 Social, draw 1 card. If you play another Social story this turn, +1 influence. | AC28: Freneau's opposition paper, subsidised by a clerkship in Jefferson's own State Department.
A29: report_manufactures | B29: The Report on Manufactures | C29: Economic story | D29: Economic | E29: 4 | F29: 1 | G29: 2 | H29: 0 | I29: 1 | J29: 0 | K29: 0 | L29: 0 | M29: 0 | N29: 0 | O29: 0 | P29: 1 | Q29: 0 | S29: 0 | T29: 0 | U29: 0 | V29: 0 | W29: 0 | Y29: 1796 | Z29: 1791 | AA29: 1 | AB29: +2 influence, +1 Economic. +1 influence for each other Economic story you play this turn. | AC29: Hamilton on why a farming republic should build factories it does not yet want.
A30: rights_of_man | B30: The Rights of Man | C30: Social story | D30: Social | E30: 4 | F30: 1 | G30: 0 | H30: 0 | I30: 0 | J30: 2 | K30: 0 | L30: 1 | M30: 0 | N30: 0 | O30: 1 | P30: 0 | Q30: 0 | S30: 0 | T30: 0 | U30: 0 | V30: 0 | W30: 0 | Y30: 1796 | Z30: 1791 | AA30: 1 | AB30: +2 Social, draw 1 card. If you play another Social story this turn, +1 influence. | AC30: Paine's defence of the French Revolution, printed in America with a note from the Secretary of State.
A31: postal_act_1792 | B31: The Postal Act of 1792 | C31: Media event | E31: 6 | F31: 2 | G31: 0 | H31: 0 | I31: 0 | J31: 0 | K31: 0 | L31: 0 | M31: 0 | N31: 0 | O31: 0 | P31: 0 | Q31: 0 | S31: 0 | T31: 0 | U31: 0 | V31: 1 | W31: 1 | X31: Political | Y31: 1796 | Z31: 1792 | AA31: 1 | AB31: Stays in play for the rest of the game. Ongoing: at the start of each of your turns, draw 1 card. Every other paper gets +1 Political influence at the start of each of its turns. | AC31: Newspapers carried anywhere in the Union for a cent or a cent and a half, and printers swapped papers postage-free. A national press became a business.
A32: citizen_genet | B32: Citizen Genet | C32: Negative story | D32: Social | E32: 3 | F32: 0 | G32: 1 | H32: 0 | I32: 0 | J32: 1 | K32: 0 | L32: 0 | M32: 0 | N32: 0 | O32: 0 | P32: 0 | Q32: 0 | R32: discard | S32: 0 | T32: 0 | U32: 0 | V32: 0 | W32: 0 | Y32: 1796 | Z32: 1793 | AA32: 1 | AB32: +1 influence, +1 Social. Attack: each rival paper discards a card at random; +1 influence if it hits any of them. Worth no prestige. | AC32: The French minister appealed to the people over Washington's head, and embarrassed his friends.
A33: democratic_societies | B33: The Democratic-Republican Societies | C33: Social story | D33: Social | E33: 3 | F33: 1 | G33: 0 | H33: 0 | I33: 0 | J33: 1 | K33: 0 | L33: 1 | M33: 0 | N33: 0 | O33: 1 | P33: 0 | Q33: 0 | S33: 1 | T33: 0 | U33: 0 | V33: 0 | W33: 0 | Y33: 1796 | Z33: 1794 | AA33: 1 | AB33: +1 Social, draw 1 card. If you play another Social story this turn, +1 influence. Defense: discard this from your hand to ignore a negative story, and draw a card. | AC33: Clubs of mechanics and farmers toasting France. Washington blamed them for the rebellion in the west.
A34: whiskey_rebellion | B34: The Whiskey Rebellion | C34: Negative story | D34: Economic | E34: 3 | F34: 0 | G34: 1 | H34: 0 | I34: 1 | J34: 0 | K34: 0 | L34: 0 | M34: 0 | N34: 0 | O34: 0 | P34: 0 | Q34: 0 | R34: discard | S34: 0 | T34: 0 | U34: 0 | V34: 0 | W34: 0 | Y34: 1796 | Z34: 1794 | AA34: 1 | AB34: +1 influence, +1 Economic. Attack: each rival paper discards a card at random; +1 influence if it hits any of them. Worth no prestige. | AC34: Thirteen thousand militia marched on western Pennsylvania to collect a tax on whiskey.
A35: jay_treaty | B35: The Jay Treaty | C35: Political story | D35: Political | E35: 4 | F35: 1 | G35: 1 | H35: 2 | I35: 0 | J35: 0 | K35: 0 | L35: 0 | M35: 0 | N35: 0 | O35: 0 | P35: 0 | Q35: 1 | S35: 0 | T35: 1 | U35: 0 | V35: 0 | W35: 0 | Y35: 1796 | Z35: 1795 | AA35: 1 | AB35: +1 influence, +2 Political. +1 Political for each election you have won. Retraction: draw a card, and you may destroy a Scandal in your hand or discard pile. | AC35: Peace with Britain, bought with the carrying trade. Burned in effigy from Boston to Charleston.
A36: alien_sedition | B36: The Alien and Sedition Acts | C36: Negative story | D36: Social | E36: 2 | F36: 0 | G36: 1 | H36: 0 | I36: 0 | J36: 0 | K36: 0 | L36: 0 | M36: 0 | N36: 0 | O36: 0 | P36: 0 | Q36: 0 | R36: discard | S36: 0 | T36: 0 | U36: 0 | V36: 0 | W36: 0 | Y36: 1800 | Z36: 1798 | AA36: 1 | AB36: +1 influence. Attack: each rival paper discards a card at random; +1 influence if it hits any of them. Worth no prestige. | AC36: Twenty-five arrests, and most of them printers. The press learned what it was worth.
A37: kentucky_resolutions | B37: The Kentucky and Virginia Resolutions | C37: Political story | D37: Political | E37: 2 | F37: 1 | G37: 1 | H37: 2 | I37: 0 | J37: 0 | K37: 0 | L37: 0 | M37: 0 | N37: 0 | O37: 0 | P37: 0 | Q37: 0 | S37: 0 | T37: 0 | U37: 0 | V37: 0 | W37: 0 | Y37: 1800 | Z37: 1798 | AA37: 1 | AB37: +1 influence, +2 Political. | AC37: Jefferson and Madison, anonymously, arguing that a state might judge the compact for itself.
A38: xyz_affair | B38: The XYZ Affair | C38: Negative story | D38: Social | E38: 4 | F38: 0 | G38: 1 | H38: 0 | I38: 0 | J38: 1 | K38: 0 | L38: 0 | M38: 0 | N38: 0 | O38: 0 | P38: 0 | Q38: 0 | R38: scandal | S38: 0 | T38: 0 | U38: 0 | V38: 0 | W38: 0 | Y38: 1800 | Z38: 1798 | AA38: 1 | AB38: +1 influence, +1 Social. Attack: each rival paper gains a Scandal; +1 influence if it hits any of them. Worth no prestige. | AC38: Millions for defence, not one cent for tribute. The best copy the Federalists ever had.
A39: marbury | B39: Marbury v. Madison | C39: Political story | D39: Political | E39: 2 | F39: 1 | G39: 1 | H39: 2 | I39: 0 | J39: 0 | K39: 0 | L39: 0 | M39: 0 | N39: 0 | O39: 0 | P39: 0 | Q39: 0 | S39: 0 | T39: 0 | U39: 0 | V39: 0 | W39: 0 | Y39: 1804 | Z39: 1803 | AA39: 1 | AB39: +1 influence, +2 Political. | AC39: Marshall gave up a commission and took the power to void an act of Congress.
A40: louisiana_purchase | B40: The Louisiana Purchase | C40: Economic story | D40: Economic | E40: 6 | F40: 2 | G40: 2 | H40: 0 | I40: 2 | J40: 0 | K40: 0 | L40: 0 | M40: 0 | N40: 4 | O40: 0 | P40: 1 | Q40: 0 | S40: 0 | T40: 0 | U40: 0 | V40: 0 | W40: 0 | Y40: 1804 | Z40: 1803 | AA40: 1 | AB40: +2 influence, +2 Economic. Gain a story costing 4 or less from the exchange. +1 influence for each other Economic story you play this turn. | AC40: Fifteen million dollars, and a strict constructionist who could not find the clause.
A41: burr_conspiracy | B41: The Burr Conspiracy | C41: Negative story | D41: Social | E41: 4 | F41: 0 | G41: 1 | H41: 0 | I41: 0 | J41: 1 | K41: 0 | L41: 0 | M41: 0 | N41: 0 | O41: 0 | P41: 0 | Q41: 0 | R41: scandal | S41: 0 | T41: 0 | U41: 0 | V41: 0 | W41: 0 | Y41: 1808 | Z41: 1807 | AA41: 1 | AB41: +1 influence, +1 Social. Attack: each rival paper gains a Scandal; +1 influence if it hits any of them. Worth no prestige. | AC41: A former Vice President tried for treason over a western empire. Jefferson wanted him hanged; Marshall let him walk.
A42: chesapeake_affair | B42: The Chesapeake Affair | C42: Social story | D42: Social | E42: 4 | F42: 1 | G42: 0 | H42: 0 | I42: 0 | J42: 2 | K42: 0 | L42: 1 | M42: 0 | N42: 0 | O42: 1 | P42: 0 | Q42: 0 | S42: 0 | T42: 0 | U42: 0 | V42: 0 | W42: 0 | Y42: 1808 | Z42: 1807 | AA42: 1 | AB42: +2 Social, draw 1 card. If you play another Social story this turn, +1 influence. | AC42: A British broadside into an American frigate in American water. Impressment made personal.
A43: embargo_act | B43: The Embargo Act | C43: Economic story | D43: Economic | E43: 3 | F43: 1 | G43: 1 | H43: 0 | I43: 1 | J43: 0 | K43: 0 | L43: 0 | M43: 1 | N43: 0 | O43: 0 | P43: 1 | Q43: 0 | S43: 0 | T43: 0 | U43: 0 | V43: 0 | W43: 0 | Y43: 1808 | Z43: 1807 | AA43: 1 | AB43: +1 influence, +1 Economic. You may destroy a card in your hand or discard pile. +1 influence for each other Economic story you play this turn. | AC43: Grass grew on the wharves of Salem. New England read it as a southern war on shipping.
A44: niles_register | B44: Niles' Weekly Register | C44: Media event | E44: 5 | F44: 1 | G44: 0 | H44: 0 | I44: 0 | J44: 0 | K44: 0 | L44: 0 | M44: 0 | N44: 0 | O44: 0 | P44: 0 | Q44: 0 | S44: 0 | T44: 0 | U44: 1 | V44: 0 | W44: 1 | X44: Political | Y44: 1812 | Z44: 1811 | AA44: 1 | AB44: Stays in play for the rest of the game. Ongoing: at the start of each of your turns, +1 influence. Every other paper gets +1 Political influence at the start of each of its turns. | AC44: A Baltimore weekly of documents, prices and speeches, read in every state and quoted by every rival.
A45: tippecanoe | B45: Tippecanoe | C45: Social story | D45: Social | E45: 4 | F45: 1 | G45: 0 | H45: 0 | I45: 0 | J45: 2 | K45: 0 | L45: 1 | M45: 0 | N45: 0 | O45: 1 | P45: 0 | Q45: 0 | S45: 0 | T45: 0 | U45: 0 | V45: 0 | W45: 0 | Y45: 1812 | Z45: 1811 | AA45: 1 | AB45: +2 Social, draw 1 card. If you play another Social story this turn, +1 influence. | AC45: Harrison's battle on the Wabash. It would still be winning him votes thirty years later.
A46: war_of_1812 | B46: Mr. Madison's War | C46: Political story | D46: Political | E46: 4 | F46: 1 | G46: 1 | H46: 2 | I46: 0 | J46: 0 | K46: 0 | L46: 0 | M46: 0 | N46: 0 | O46: 0 | P46: 0 | Q46: 1 | S46: 0 | T46: 1 | U46: 0 | V46: 0 | W46: 0 | Y46: 1812 | Z46: 1812 | AA46: 1 | AB46: +1 influence, +2 Political. +1 Political for each election you have won. Retraction: draw a card, and you may destroy a Scandal in your hand or discard pile. | AC46: The second war of independence, or a Virginian adventure at New England expense.
A47: gerrymander | B47: The Gerrymander | C47: Negative story | D47: Political | E47: 4 | F47: 0 | G47: 1 | H47: 1 | I47: 0 | J47: 0 | K47: 0 | L47: 0 | M47: 0 | N47: 0 | O47: 0 | P47: 0 | Q47: 0 | R47: scandal | S47: 0 | T47: 0 | U47: 0 | V47: 0 | W47: 0 | Y47: 1812 | Z47: 1812 | AA47: 1 | AB47: +1 influence, +1 Political. Attack: each rival paper gains a Scandal; +1 influence if it hits any of them. Worth no prestige. | AC47: A Massachusetts district drawn in the shape of a salamander, signed into law by Governor Gerry.
A48: hartford_convention | B48: The Hartford Convention | C48: Negative story | D48: Social | E48: 2 | F48: 0 | G48: 1 | H48: 0 | I48: 0 | J48: 0 | K48: 0 | L48: 0 | M48: 0 | N48: 0 | O48: 0 | P48: 0 | Q48: 0 | R48: discard | S48: 0 | T48: 0 | U48: 0 | V48: 0 | W48: 0 | Y48: 1816 | Z48: 1814 | AA48: 1 | AB48: +1 influence. Attack: each rival paper discards a card at random; +1 influence if it hits any of them. Worth no prestige. | AC48: New England Federalists met in secret to discuss leaving, and destroyed their own party.
A49: treaty_of_ghent | B49: The Treaty of Ghent | C49: Political story | D49: Political | E49: 5 | F49: 1 | G49: 2 | H49: 2 | I49: 0 | J49: 0 | K49: 2 | L49: 0 | M49: 0 | N49: 0 | O49: 0 | P49: 0 | Q49: 0 | S49: 0 | T49: 1 | U49: 0 | V49: 0 | W49: 0 | Y49: 1816 | Z49: 1814 | AA49: 1 | AB49: +2 influence, +2 Political, +2 Campaign (elections only). Retraction: draw a card, and you may destroy a Scandal in your hand or discard pile. | AC49: Status quo ante bellum. Everyone claimed to have won.
A50: second_bank | B50: The Second Bank of the United States | C50: Economic story | D50: Economic | E50: 5 | F50: 1 | G50: 2 | H50: 0 | I50: 1 | J50: 0 | K50: 0 | L50: 0 | M50: 1 | N50: 0 | O50: 0 | P50: 1 | Q50: 0 | S50: 0 | T50: 0 | U50: 0 | V50: 0 | W50: 0 | Y50: 1816 | Z50: 1816 | AA50: 1 | AB50: +2 influence, +1 Economic. You may destroy a card in your hand or discard pile. +1 influence for each other Economic story you play this turn. | AC50: A national currency, and a monster, depending on which paper you took.
A51: tariff_of_1816 | B51: The Tariff of 1816 | C51: Economic story | D51: Economic | E51: 4 | F51: 1 | G51: 2 | H51: 0 | I51: 1 | J51: 0 | K51: 0 | L51: 0 | M51: 0 | N51: 0 | O51: 0 | P51: 1 | Q51: 0 | S51: 0 | T51: 0 | U51: 0 | V51: 0 | W51: 0 | Y51: 1816 | Z51: 1816 | AA51: 1 | AB51: +2 influence, +1 Economic. +1 influence for each other Economic story you play this turn. | AC51: The first protective tariff, passed by southerners who had learned what a blockade does.
A52: cumberland_road | B52: The Cumberland Road | C52: Economic story | D52: Economic | E52: 5 | F52: 1 | G52: 2 | H52: 0 | I52: 1 | J52: 0 | K52: 0 | L52: 0 | M52: 1 | N52: 0 | O52: 0 | P52: 1 | Q52: 0 | S52: 0 | T52: 0 | U52: 0 | V52: 0 | W52: 0 | Y52: 1820 | Z52: 1818 | AA52: 1 | AB52: +2 influence, +1 Economic. You may destroy a card in your hand or discard pile. +1 influence for each other Economic story you play this turn. | AC52: A federal highway reaches the Ohio at Wheeling. Who pays to mend it is another question.
A53: mcculloch | B53: McCulloch v. Maryland | C53: Economic story | D53: Economic | E53: 3 | F53: 1 | G53: 1 | H53: 0 | I53: 1 | J53: 0 | K53: 0 | L53: 0 | M53: 1 | N53: 0 | O53: 0 | P53: 1 | Q53: 0 | S53: 0 | T53: 0 | U53: 0 | V53: 0 | W53: 0 | Y53: 1820 | Z53: 1819 | AA53: 1 | AB53: +1 influence, +1 Economic. You may destroy a card in your hand or discard pile. +1 influence for each other Economic story you play this turn. | AC53: Maryland taxed the national bank; Marshall ruled the power to tax is the power to destroy.
A54: adams_onis | B54: The Adams-Onis Treaty | C54: Political story | D54: Political | E54: 5 | F54: 1 | G54: 2 | H54: 2 | I54: 0 | J54: 0 | K54: 2 | L54: 0 | M54: 0 | N54: 0 | O54: 0 | P54: 0 | Q54: 0 | S54: 0 | T54: 1 | U54: 0 | V54: 0 | W54: 0 | Y54: 1820 | Z54: 1819 | AA54: 1 | AB54: +2 influence, +2 Political, +2 Campaign (elections only). Retraction: draw a card, and you may destroy a Scandal in your hand or discard pile. | AC54: Spain gives up Florida, and a line is drawn to the Pacific on paper.
A55: panic_of_1819 | B55: The Panic of 1819 | C55: Negative story | D55: Economic | E55: 5 | F55: 0 | G55: 2 | H55: 0 | I55: 1 | J55: 0 | K55: 0 | L55: 0 | M55: 0 | N55: 0 | O55: 0 | P55: 0 | Q55: 0 | R55: scandal | S55: 0 | T55: 0 | U55: 0 | V55: 0 | W55: 0 | Y55: 1820 | Z55: 1819 | AA55: 1 | AB55: +2 influence, +1 Economic. Attack: each rival paper gains a Scandal; +1 influence if it hits any of them. Worth no prestige. | AC55: The Bank called in its loans and the west discovered what credit was.
A56: missouri_compromise | B56: The Missouri Compromise | C56: Social story | D56: Social | E56: 4 | F56: 1 | G56: 0 | H56: 0 | I56: 0 | J56: 2 | K56: 0 | L56: 1 | M56: 0 | N56: 0 | O56: 1 | P56: 0 | Q56: 0 | S56: 0 | T56: 0 | U56: 0 | V56: 0 | W56: 0 | Y56: 1820 | Z56: 1820 | AA56: 1 | AB56: +2 Social, draw 1 card. If you play another Social story this turn, +1 influence. | AC56: A fire bell in the night, muffled for thirty years by a line at 36 degrees 30 minutes.
A57: denmark_vesey | B57: Denmark Vesey | C57: Negative story | D57: Social | E57: 2 | F57: 0 | G57: 1 | H57: 0 | I57: 0 | J57: 0 | K57: 0 | L57: 0 | M57: 0 | N57: 0 | O57: 0 | P57: 0 | Q57: 0 | R57: discard | S57: 0 | T57: 0 | U57: 0 | V57: 0 | W57: 0 | Y57: 1824 | Z57: 1822 | AA57: 1 | AB57: +1 influence. Attack: each rival paper discards a card at random; +1 influence if it hits any of them. Worth no prestige. | AC57: Charleston hangs thirty-five men for a rising that never happened, and tightens every law it has.
A58: crawford_radicals | B58: The Crawford Radicals | C58: Negative story | D58: Political | E58: 3 | F58: 0 | G58: 1 | H58: 1 | I58: 0 | J58: 0 | K58: 0 | L58: 0 | M58: 0 | N58: 0 | O58: 0 | P58: 0 | Q58: 0 | R58: discard | S58: 0 | T58: 0 | U58: 0 | V58: 0 | W58: 0 | Y58: 1824 | Z58: 1823 | AA58: 1 | AB58: +1 influence, +1 Political. Attack: each rival paper discards a card at random; +1 influence if it hits any of them. Worth no prestige. | AC58: The Old Republicans rallied behind Crawford and the caucus. A stroke left their man half-blind before the canvass began.
A59: monroe_doctrine | B59: The Monroe Doctrine | C59: Political story | D59: Political | E59: 4 | F59: 1 | G59: 1 | H59: 2 | I59: 0 | J59: 0 | K59: 0 | L59: 0 | M59: 0 | N59: 0 | O59: 0 | P59: 0 | Q59: 1 | S59: 0 | T59: 1 | U59: 0 | V59: 0 | W59: 0 | Y59: 1824 | Z59: 1823 | AA59: 1 | AB59: +1 influence, +2 Political. +1 Political for each election you have won. Retraction: draw a card, and you may destroy a Scandal in your hand or discard pile. | AC59: A hemisphere closed to European colonisation, announced by a nation that could not enforce it.
A60: american_system | B60: The American System | C60: Economic story | D60: Economic | E60: 5 | F60: 1 | G60: 2 | H60: 0 | I60: 1 | J60: 0 | K60: 0 | L60: 0 | M60: 1 | N60: 0 | O60: 0 | P60: 1 | Q60: 0 | S60: 0 | T60: 0 | U60: 0 | V60: 0 | W60: 0 | Y60: 1824 | Z60: 1824 | AA60: 1 | AB60: +2 influence, +1 Economic. You may destroy a card in your hand or discard pile. +1 influence for each other Economic story you play this turn. | AC60: Clay wanted tariffs, a bank and roads, and to be remembered for all three.
A61: erie_canal | B61: The Erie Canal | C61: Economic story | D61: Economic | E61: 6 | F61: 2 | G61: 2 | H61: 0 | I61: 2 | J61: 0 | K61: 0 | L61: 0 | M61: 0 | N61: 4 | O61: 0 | P61: 1 | Q61: 0 | S61: 0 | T61: 0 | U61: 0 | V61: 0 | W61: 0 | Y61: 1828 | Z61: 1825 | AA61: 1 | AB61: +2 influence, +2 Economic. Gain a story costing 4 or less from the exchange. +1 influence for each other Economic story you play this turn. | AC61: Three hundred and sixty-three miles, and the price of flour in New York fell by half.
A62: lowell_mills | B62: The Lowell Mills | C62: Social story | D62: Social | E62: 6 | F62: 2 | G62: 0 | H62: 0 | I62: 0 | J62: 2 | K62: 0 | L62: 1 | M62: 0 | N62: 0 | O62: 2 | P62: 0 | Q62: 0 | S62: 1 | T62: 0 | U62: 0 | V62: 0 | W62: 0 | Y62: 1828 | Z62: 1826 | AA62: 1 | AB62: +2 Social, draw 1 card. If you play another Social story this turn, +2 influence. Defense: discard this from your hand to ignore a negative story, and draw a card. | AC62: Textile capital with a moral architecture attached, and a constituency for protection.
A63: freedoms_journal | B63: Freedom's Journal | C63: Social story | D63: Social | E63: 3 | F63: 1 | G63: 0 | H63: 0 | I63: 0 | J63: 1 | K63: 0 | L63: 1 | M63: 0 | N63: 0 | O63: 1 | P63: 0 | Q63: 0 | S63: 1 | T63: 0 | U63: 0 | V63: 0 | W63: 0 | Y63: 1828 | Z63: 1827 | AA63: 1 | AB63: +1 Social, draw 1 card. If you play another Social story this turn, +1 influence. Defense: discard this from your hand to ignore a negative story, and draw a card. | AC63: The first newspaper owned and edited by Black Americans: "We wish to plead our own cause."
A64: anti_masonic_party | B64: The Anti-Masonic Party | C64: Negative story | D64: Political | E64: 3 | F64: 0 | G64: 1 | H64: 1 | I64: 0 | J64: 0 | K64: 0 | L64: 0 | M64: 0 | N64: 0 | O64: 0 | P64: 0 | Q64: 0 | R64: discard | S64: 0 | T64: 0 | U64: 0 | V64: 0 | W64: 0 | Y64: 1828 | Z64: 1828 | AA64: 1 | AB64: +1 influence, +1 Political. Attack: each rival paper discards a card at random; +1 influence if it hits any of them. Worth no prestige. | AC64: A stonemason vanishes in western New York, and a crusade against secret societies becomes a party.
A65: cherokee_phoenix | B65: The Cherokee Phoenix | C65: Social story | D65: Social | E65: 3 | F65: 1 | G65: 0 | H65: 0 | I65: 0 | J65: 1 | K65: 0 | L65: 1 | M65: 0 | N65: 0 | O65: 1 | P65: 0 | Q65: 0 | S65: 1 | T65: 0 | U65: 0 | V65: 0 | W65: 0 | Y65: 1828 | Z65: 1828 | AA65: 1 | AB65: +1 Social, draw 1 card. If you play another Social story this turn, +1 influence. Defense: discard this from your hand to ignore a negative story, and draw a card. | AC65: Printed at New Echota in English and Sequoyah's syllabary, while Georgia eyes the land beneath it.
A66: sc_exposition | B66: The South Carolina Exposition | C66: Political story | D66: Political | E66: 2 | F66: 1 | G66: 1 | H66: 2 | I66: 0 | J66: 0 | K66: 0 | L66: 0 | M66: 0 | N66: 0 | O66: 0 | P66: 0 | Q66: 0 | S66: 0 | T66: 0 | U66: 0 | V66: 0 | W66: 0 | Y66: 1828 | Z66: 1828 | AA66: 1 | AB66: +1 influence, +2 Political. | AC66: Calhoun, anonymously and while Vice President, on the right of a state to say no.
A67: tariff_abominations | B67: The Tariff of Abominations | C67: Economic story | D67: Economic | E67: 3 | F67: 1 | G67: 1 | H67: 0 | I67: 1 | J67: 0 | K67: 0 | L67: 0 | M67: 1 | N67: 0 | O67: 0 | P67: 1 | Q67: 0 | S67: 0 | T67: 0 | U67: 0 | V67: 0 | W67: 0 | Y67: 1828 | Z67: 1828 | AA67: 1 | AB67: +1 influence, +1 Economic. You may destroy a card in your hand or discard pile. +1 influence for each other Economic story you play this turn. | AC67: Written to be so bad it would fail, and passed anyway.
A68: cotton_boom | B68: The Cotton Boom | C68: Economic story | D68: Economic | E68: 8 | F68: 3 | G68: 4 | H68: 0 | I68: 2 | J68: 0 | K68: 0 | L68: 0 | M68: 0 | N68: 5 | O68: 0 | P68: 1 | Q68: 0 | S68: 0 | T68: 0 | U68: 0 | V68: 0 | W68: 0 | Y68: 1832 | Z68: 1830 | AA68: 1 | AB68: +4 influence, +2 Economic. Gain a story costing 5 or less from the exchange. +1 influence for each other Economic story you play this turn. | AC68: Two thirds of American exports, sold to Liverpool. Independence was never that simple.
A69: indian_removal | B69: The Indian Removal Act | C69: Political story | D69: Political | E69: 4 | F69: 1 | G69: 1 | H69: 2 | I69: 0 | J69: 0 | K69: 0 | L69: 0 | M69: 0 | N69: 0 | O69: 0 | P69: 0 | Q69: 1 | S69: 0 | T69: 1 | U69: 0 | V69: 0 | W69: 0 | Y69: 1832 | Z69: 1830 | AA69: 1 | AB69: +1 influence, +2 Political. +1 Political for each election you have won. Retraction: draw a card, and you may destroy a Scandal in your hand or discard pile. | AC69: Congress votes the money to move the southern nations west, and calls it voluntary.
A70: webster_hayne | B70: The Webster-Hayne Debate | C70: Political story | D70: Political | E70: 5 | F70: 1 | G70: 2 | H70: 2 | I70: 0 | J70: 0 | K70: 2 | L70: 0 | M70: 0 | N70: 0 | O70: 0 | P70: 0 | Q70: 0 | S70: 0 | T70: 1 | U70: 0 | V70: 0 | W70: 0 | Y70: 1832 | Z70: 1830 | AA70: 1 | AB70: +2 influence, +2 Political, +2 Campaign (elections only). Retraction: draw a card, and you may destroy a Scandal in your hand or discard pile. | AC70: Liberty and Union, now and forever, one and inseparable. It sold very well in print.
A71: the_liberator | B71: The Liberator | C71: Social story | D71: Social | E71: 5 | F71: 1 | G71: 1 | H71: 0 | I71: 0 | J71: 2 | K71: 0 | L71: 1 | M71: 0 | N71: 0 | O71: 0 | P71: 0 | Q71: 0 | S71: 0 | T71: 0 | U71: 0 | V71: 0 | W71: 0 | Y71: 1832 | Z71: 1831 | AA71: 1 | AB71: +1 influence, +2 Social, draw 1 card. | AC71: Garrison's weekly in Boston: "I will not equivocate - I will not excuse - and I will be heard."
A72: bank_war | B72: The Bank War | C72: Economic story | D72: Economic | E72: 5 | F72: 1 | G72: 2 | H72: 0 | I72: 1 | J72: 0 | K72: 0 | L72: 0 | M72: 1 | N72: 0 | O72: 0 | P72: 1 | Q72: 0 | S72: 0 | T72: 0 | U72: 0 | V72: 0 | W72: 0 | Y72: 1832 | Z72: 1832 | AA72: 1 | AB72: +2 influence, +1 Economic. You may destroy a card in your hand or discard pile. +1 influence for each other Economic story you play this turn. | AC72: The Bank tried to make itself the election. Jackson was delighted to oblige.
A73: force_bill | B73: The Force Bill | C73: Political story | D73: Political | E73: 3 | F73: 1 | G73: 1 | H73: 2 | I73: 0 | J73: 0 | K73: 1 | L73: 0 | M73: 0 | N73: 0 | O73: 0 | P73: 0 | Q73: 0 | S73: 0 | T73: 1 | U73: 0 | V73: 0 | W73: 0 | Y73: 1836 | Z73: 1833 | AA73: 1 | AB73: +1 influence, +2 Political, +1 Campaign (elections only). Retraction: draw a card, and you may destroy a Scandal in your hand or discard pile. | AC73: Authority to collect the tariff by arms, signed the same day as the compromise that made it moot.
A74: penny_press | B74: The Penny Press | C74: Media event | E74: 6 | F74: 2 | G74: 0 | H74: 0 | I74: 0 | J74: 0 | K74: 0 | L74: 0 | M74: 0 | N74: 0 | O74: 0 | P74: 0 | Q74: 0 | S74: 0 | T74: 0 | U74: 0 | V74: 1 | W74: 1 | X74: Social | Y74: 1836 | Z74: 1833 | AA74: 1 | AB74: Stays in play for the rest of the game. Ongoing: at the start of each of your turns, draw 1 card. Every other paper gets +1 Social influence at the start of each of its turns. | AC74: A cent a copy, sold in the street rather than by subscription. Your own trade, industrialised.
A75: gag_rule | B75: The Gag Rule | C75: Negative story | D75: Social | E75: 3 | F75: 0 | G75: 1 | H75: 0 | I75: 0 | J75: 1 | K75: 0 | L75: 0 | M75: 0 | N75: 0 | O75: 0 | P75: 0 | Q75: 0 | R75: discard | S75: 0 | T75: 0 | U75: 0 | V75: 0 | W75: 0 | Y75: 1836 | Z75: 1836 | AA75: 1 | AB75: +1 influence, +1 Social. Attack: each rival paper discards a card at random; +1 influence if it hits any of them. Worth no prestige. | AC75: Antislavery petitions tabled unread, which turned the right of petition into the argument.
A76: specie_circular | B76: The Specie Circular | C76: Economic story | D76: Economic | E76: 5 | F76: 1 | G76: 2 | H76: 0 | I76: 1 | J76: 0 | K76: 0 | L76: 0 | M76: 1 | N76: 0 | O76: 0 | P76: 1 | Q76: 0 | S76: 0 | T76: 0 | U76: 0 | V76: 0 | W76: 0 | Y76: 1836 | Z76: 1836 | AA76: 1 | AB76: +2 influence, +1 Economic. You may destroy a card in your hand or discard pile. +1 influence for each other Economic story you play this turn. | AC76: Public land for gold and silver only. The paper economy discovered how thin it was.
A77: panic_of_1837 | B77: The Panic of 1837 | C77: Negative story | D77: Economic | E77: 6 | F77: 0 | G77: 2 | H77: 0 | I77: 2 | J77: 0 | K77: 0 | L77: 0 | M77: 0 | N77: 0 | O77: 0 | P77: 0 | Q77: 0 | R77: scandal | S77: 0 | T77: 0 | U77: 0 | V77: 0 | W77: 0 | Y77: 1840 | Z77: 1837 | AA77: 1 | AB77: +2 influence, +2 Economic. Attack: each rival paper gains a Scandal; +1 influence if it hits any of them. Worth no prestige. | AC77: Six years of depression, and a president renamed Van Ruin for the duration.
A78: amistad | B78: The Amistad | C78: Social story | D78: Social | E78: 4 | F78: 1 | G78: 0 | H78: 0 | I78: 0 | J78: 2 | K78: 0 | L78: 1 | M78: 0 | N78: 0 | O78: 1 | P78: 0 | Q78: 0 | S78: 0 | T78: 0 | U78: 0 | V78: 0 | W78: 0 | Y78: 1840 | Z78: 1839 | AA78: 1 | AB78: +2 Social, draw 1 card. If you play another Social story this turn, +1 influence. | AC78: Africans who seized a slave ship were tried in Connecticut. John Quincy Adams took their case to the Supreme Court.
A79: log_cabin_campaign | B79: Log Cabin and Hard Cider | C79: Social story | D79: Social | E79: 6 | F79: 2 | G79: 0 | H79: 0 | I79: 0 | J79: 2 | K79: 0 | L79: 1 | M79: 0 | N79: 0 | O79: 2 | P79: 0 | Q79: 0 | S79: 1 | T79: 0 | U79: 0 | V79: 0 | W79: 0 | Y79: 1840 | Z79: 1840 | AA79: 1 | AB79: +2 Social, draw 1 card. If you play another Social story this turn, +2 influence. Defense: discard this from your hand to ignore a negative story, and draw a card. | AC79: The Whigs sold a Virginia planter's son as a frontiersman, and printed songbooks by the hundred thousand.
A80: tyler_vetoes | B80: His Accidency's Vetoes | C80: Negative story | D80: Political | E80: 4 | F80: 0 | G80: 1 | H80: 1 | I80: 0 | J80: 0 | K80: 0 | L80: 0 | M80: 0 | N80: 0 | O80: 0 | P80: 0 | Q80: 0 | R80: scandal | S80: 0 | T80: 0 | U80: 0 | V80: 0 | W80: 0 | Y80: 1844 | Z80: 1841 | AA80: 1 | AB80: +1 influence, +1 Political. Attack: each rival paper gains a Scandal; +1 influence if it hits any of them. Worth no prestige. | AC80: Tyler vetoed the Whig bank twice. His cabinet resigned and his party expelled him.
A81: dorr_rebellion | B81: The Dorr Rebellion | C81: Negative story | D81: Social | E81: 4 | F81: 0 | G81: 1 | H81: 0 | I81: 0 | J81: 1 | K81: 0 | L81: 0 | M81: 0 | N81: 0 | O81: 0 | P81: 0 | Q81: 0 | R81: scandal | S81: 0 | T81: 0 | U81: 0 | V81: 0 | W81: 0 | Y81: 1844 | Z81: 1842 | AA81: 1 | AB81: +1 influence, +1 Social. Attack: each rival paper gains a Scandal; +1 influence if it hits any of them. Worth no prestige. | AC81: Rhode Island briefly had two governors, over who was allowed to vote.
A82: webster_ashburton | B82: The Webster-Ashburton Treaty | C82: Economic story | D82: Economic | E82: 5 | F82: 1 | G82: 2 | H82: 0 | I82: 1 | J82: 0 | K82: 0 | L82: 0 | M82: 1 | N82: 0 | O82: 0 | P82: 1 | Q82: 0 | S82: 0 | T82: 0 | U82: 0 | V82: 0 | W82: 0 | Y82: 1844 | Z82: 1842 | AA82: 1 | AB82: +2 influence, +1 Economic. You may destroy a card in your hand or discard pile. +1 influence for each other Economic story you play this turn. | AC82: The Maine border settled by negotiation, without the war the papers had been promising.
A83: telegraph | B83: The Magnetic Telegraph | C83: Media event | E83: 7 | F83: 2 | G83: 0 | H83: 0 | I83: 0 | J83: 0 | K83: 0 | L83: 0 | M83: 0 | N83: 0 | O83: 0 | P83: 0 | Q83: 0 | S83: 0 | T83: 0 | U83: 1 | V83: 1 | W83: 1 | Y83: 1844 | Z83: 1844 | AA83: 1 | AB83: Stays in play for the rest of the game. Ongoing: at the start of each of your turns, +1 influence and draw 1 card. Every other paper gets +1 influence at the start of each of its turns. | AC83: Morse's line from Washington to Baltimore. News now moved faster than the mail that carried the papers.
A84: texas_annexation | B84: The Annexation of Texas | C84: Political story | D84: Political | E84: 6 | F84: 2 | G84: 2 | H84: 3 | I84: 0 | J84: 0 | K84: 0 | L84: 0 | M84: 0 | N84: 0 | O84: 0 | P84: 0 | Q84: 1 | S84: 0 | T84: 1 | U84: 0 | V84: 0 | W84: 0 | Y84: 1848 | Z84: 1845 | AA84: 1 | AB84: +2 influence, +3 Political. +1 Political for each election you have won. Retraction: draw a card, and you may destroy a Scandal in your hand or discard pile. | AC84: Admitted by joint resolution because a treaty could not get two thirds.
A85: oregon_treaty | B85: Fifty-four Forty | C85: Social story | D85: Social | E85: 5 | F85: 1 | G85: 1 | H85: 0 | I85: 0 | J85: 2 | K85: 0 | L85: 1 | M85: 0 | N85: 0 | O85: 0 | P85: 0 | Q85: 0 | S85: 0 | T85: 0 | U85: 0 | V85: 0 | W85: 0 | Y85: 1848 | Z85: 1846 | AA85: 1 | AB85: +1 influence, +2 Social, draw 1 card. | AC85: Fifty-four forty or fight, settled quietly at forty-nine.
A86: associated_press | B86: The Associated Press | C86: Media event | E86: 6 | F86: 2 | G86: 0 | H86: 0 | I86: 0 | J86: 0 | K86: 0 | L86: 0 | M86: 0 | N86: 0 | O86: 0 | P86: 0 | Q86: 0 | S86: 0 | T86: 0 | U86: 2 | V86: 0 | W86: 1 | Y86: 1848 | Z86: 1846 | AA86: 1 | AB86: Stays in play for the rest of the game. Ongoing: at the start of each of your turns, +2 influence. Every other paper gets +1 influence at the start of each of its turns. | AC86: New York papers pooled the cost of news from the Mexican War, and sold it to everyone else.
A87: mexican_war | B87: The Mexican War | C87: Political story | D87: Political | E87: 6 | F87: 2 | G87: 2 | H87: 3 | I87: 0 | J87: 0 | K87: 0 | L87: 0 | M87: 0 | N87: 0 | O87: 0 | P87: 0 | Q87: 1 | S87: 0 | T87: 1 | U87: 0 | V87: 0 | W87: 0 | Y87: 1848 | Z87: 1846 | AA87: 1 | AB87: +2 influence, +3 Political. +1 Political for each election you have won. Retraction: draw a card, and you may destroy a Scandal in your hand or discard pile. | AC87: American blood shed on American soil, if you accepted where the soil began.
A88: wilmot_proviso | B88: The Wilmot Proviso | C88: Social story | D88: Social | E88: 3 | F88: 1 | G88: 0 | H88: 0 | I88: 0 | J88: 1 | K88: 0 | L88: 1 | M88: 0 | N88: 0 | O88: 1 | P88: 0 | Q88: 0 | S88: 1 | T88: 0 | U88: 0 | V88: 0 | W88: 0 | Y88: 1848 | Z88: 1846 | AA88: 1 | AB88: +1 Social, draw 1 card. If you play another Social story this turn, +1 influence. Defense: discard this from your hand to ignore a negative story, and draw a card. | AC88: Neither slavery nor involuntary servitude in any territory taken from Mexico. It passed the House eight times.
A89: rotary_press | B89: The Rotary Press | C89: Media event | E89: 7 | F89: 2 | G89: 0 | H89: 0 | I89: 0 | J89: 0 | K89: 0 | L89: 0 | M89: 0 | N89: 0 | O89: 0 | P89: 0 | Q89: 0 | S89: 0 | T89: 0 | U89: 1 | V89: 1 | W89: 1 | X89: Economic | Y89: 1848 | Z89: 1847 | AA89: 1 | AB89: Stays in play for the rest of the game. Ongoing: at the start of each of your turns, +1 influence and draw 1 card. Every other paper gets +1 Economic influence at the start of each of its turns. | AC89: Hoe's type-revolving press printed thousands of sheets an hour. Circulation was now limited by readers, not machines.
A90: free_soil | B90: The Free Soil Party | C90: Economic story | D90: Economic | E90: 5 | F90: 1 | G90: 2 | H90: 0 | I90: 1 | J90: 0 | K90: 0 | L90: 0 | M90: 1 | N90: 0 | O90: 0 | P90: 1 | Q90: 0 | S90: 0 | T90: 0 | U90: 0 | V90: 0 | W90: 0 | Y90: 1848 | Z90: 1848 | AA90: 1 | AB90: +2 influence, +1 Economic. You may destroy a card in your hand or discard pile. +1 influence for each other Economic story you play this turn. | AC90: Free soil, free speech, free labor and free men. Van Buren ran on it and handed New York to Taylor.
A91: gold_rush | B91: The Gold Rush | C91: Economic story | D91: Economic | E91: 8 | F91: 3 | G91: 4 | H91: 0 | I91: 2 | J91: 0 | K91: 0 | L91: 0 | M91: 0 | N91: 5 | O91: 0 | P91: 1 | Q91: 0 | S91: 0 | T91: 0 | U91: 0 | V91: 0 | W91: 0 | Y91: 1852 | Z91: 1849 | AA91: 1 | AB91: +4 influence, +2 Economic. Gain a story costing 5 or less from the exchange. +1 influence for each other Economic story you play this turn. | AC91: Ninety thousand people crossed a continent in a year, and California wanted in at once.
A92: compromise_1850 | B92: The Compromise of 1850 | C92: Economic story | D92: Economic | E92: 5 | F92: 1 | G92: 2 | H92: 0 | I92: 1 | J92: 0 | K92: 0 | L92: 0 | M92: 1 | N92: 0 | O92: 0 | P92: 1 | Q92: 0 | S92: 0 | T92: 0 | U92: 0 | V92: 0 | W92: 0 | Y92: 1852 | Z92: 1850 | AA92: 1 | AB92: +2 influence, +1 Economic. You may destroy a card in your hand or discard pile. +1 influence for each other Economic story you play this turn. | AC92: Five bills passed separately because no majority existed for all five together.
A93: fugitive_slave_act | B93: The Fugitive Slave Act | C93: Negative story | D93: Social | E93: 4 | F93: 0 | G93: 1 | H93: 0 | I93: 0 | J93: 1 | K93: 0 | L93: 0 | M93: 0 | N93: 0 | O93: 0 | P93: 0 | Q93: 0 | R93: scandal | S93: 0 | T93: 0 | U93: 0 | V93: 0 | W93: 0 | Y93: 1852 | Z93: 1850 | AA93: 1 | AB93: +1 influence, +1 Social. Attack: each rival paper gains a Scandal; +1 influence if it hits any of them. Worth no prestige. | AC93: Federal power used against the North on behalf of the South, and it radicalised both.
A94: georgia_platform | B94: The Georgia Platform | C94: Political story | D94: Political | E94: 4 | F94: 1 | G94: 1 | H94: 2 | I94: 0 | J94: 0 | K94: 0 | L94: 0 | M94: 0 | N94: 0 | O94: 0 | P94: 0 | Q94: 1 | S94: 0 | T94: 1 | U94: 0 | V94: 0 | W94: 0 | Y94: 1852 | Z94: 1850 | AA94: 1 | AB94: +1 influence, +2 Political. +1 Political for each election you have won. Retraction: draw a card, and you may destroy a Scandal in your hand or discard pile. | AC94: Georgia would accept the Compromise, and named the conditions under which it would not.
A95: nashville_convention | B95: The Nashville Convention | C95: Negative story | D95: Political | E95: 3 | F95: 0 | G95: 1 | H95: 1 | I95: 0 | J95: 0 | K95: 0 | L95: 0 | M95: 0 | N95: 0 | O95: 0 | P95: 0 | Q95: 0 | R95: discard | S95: 0 | T95: 0 | U95: 0 | V95: 0 | W95: 0 | Y95: 1852 | Z95: 1850 | AA95: 1 | AB95: +1 influence, +1 Political. Attack: each rival paper discards a card at random; +1 influence if it hits any of them. Worth no prestige. | AC95: Nine states met to consider what the South would do if the territories were closed.
A96: cheap_postage | B96: The Cheap Postage Act | C96: Media event | E96: 5 | F96: 1 | G96: 0 | H96: 0 | I96: 0 | J96: 0 | K96: 0 | L96: 0 | M96: 0 | N96: 0 | O96: 0 | P96: 0 | Q96: 0 | S96: 0 | T96: 0 | U96: 1 | V96: 0 | W96: 1 | X96: Social | Y96: 1852 | Z96: 1851 | AA96: 1 | AB96: Stays in play for the rest of the game. Ongoing: at the start of each of your turns, +1 influence. Every other paper gets +1 Social influence at the start of each of its turns. | AC96: Congress cut newspaper postage again, and the country weekly reached its county for next to nothing.
A97: uncle_toms_cabin | B97: Uncle Tom's Cabin | C97: Social story | D97: Social | E97: 7 | F97: 2 | G97: 1 | H97: 0 | I97: 0 | J97: 2 | K97: 0 | L97: 2 | M97: 0 | N97: 0 | O97: 1 | P97: 0 | Q97: 0 | S97: 0 | T97: 0 | U97: 0 | V97: 0 | W97: 0 | Y97: 1852 | Z97: 1852 | AA97: 1 | AB97: +1 influence, +2 Social, draw 2 cards. If you play another Social story this turn, +1 influence. | AC97: Three hundred thousand copies in a year. The best-selling argument any of you ever printed.
A98: transcontinental_railroad | B98: The Pacific Railroad Surveys | C98: Economic story | D98: Economic | E98: 7 | F98: 2 | G98: 3 | H98: 0 | I98: 2 | J98: 0 | K98: 0 | L98: 0 | M98: 0 | N98: 0 | O98: 0 | P98: 1 | Q98: 0 | S98: 0 | T98: 0 | U98: 0 | V98: 0 | W98: 0 | Y98: 1856 | Z98: 1853 | AA98: 1 | AB98: +3 influence, +2 Economic. +1 influence for each other Economic story you play this turn. | AC98: Every proposed route was an argument about which section would own the future.
A99: gadsden_purchase | B99: The Gadsden Purchase | C99: Economic story | D99: Economic | E99: 6 | F99: 2 | G99: 2 | H99: 0 | I99: 2 | J99: 0 | K99: 0 | L99: 0 | M99: 0 | N99: 4 | O99: 0 | P99: 1 | Q99: 0 | S99: 0 | T99: 0 | U99: 0 | V99: 0 | W99: 0 | Y99: 1856 | Z99: 1854 | AA99: 1 | AB99: +2 influence, +2 Economic. Gain a story costing 4 or less from the exchange. +1 influence for each other Economic story you play this turn. | AC99: Ten million dollars of desert, bought for a southern railroad route.
A100: kansas_nebraska | B100: The Kansas-Nebraska Act | C100: Political story | D100: Political | E100: 4 | F100: 1 | G100: 1 | H100: 2 | I100: 0 | J100: 0 | K100: 0 | L100: 0 | M100: 0 | N100: 0 | O100: 0 | P100: 0 | Q100: 1 | S100: 0 | T100: 1 | U100: 0 | V100: 0 | W100: 0 | Y100: 1856 | Z100: 1854 | AA100: 1 | AB100: +1 influence, +2 Political. +1 Political for each election you have won. Retraction: draw a card, and you may destroy a Scandal in your hand or discard pile. | AC100: Douglas repealed the Missouri line to get his railroad, and detonated the party system.
...

Sheet Elections
A1: space | B1: year | C1: era | D1: card_name | E1: Prestige | F1: Prestige per office | G1: Influence (plain) | H1: Candidate-theme influence | I1: nation | J1: nation_theme | K1: nation_threshold | L1: states | M1: states_theme | N1: states_threshold | O1: historical_winner | P1: p_draw | Q1: p_trash | R1: p_trash_draw | S1: p_gain_upto | T1: p_recover | U1: p_per_kind | V1: p_scry | W1: p_stay_gen | X1: p_attack | Y1: power_text | Z1: fa_kind | AA1: fa_n | AB1: fa_name | AC1: fa_text | AD1: card_text
A2: 1 | B2: 1796 | C2: I | D2: The Farewell Address | E2: 3 | F2: 0 | G2: 2 | H2: 2 | I2: John Adams | J2: Political | K2: 8 | L2: Thomas Jefferson | M2: Social | N2: 10 | O2: nation | P2: 1 | Q2: 0 | R2: 0 | S2: 0 | T2: 0 | U2: 0 | V2: 0 | W2: 0 | Y2: +2 influence, draw a card. | AA2: 0 | AD2: +2 influence, draw a card. Also +2 of the elected candidate's theme. Worth 3 prestige.
A3: 2 | B3: 1800 | C3: I | D3: The Revolution of 1800 | E3: 3 | F3: 0 | G3: 2 | H3: 2 | I3: John Adams | J3: Social | K3: 10 | L3: Thomas Jefferson | M3: Political | N3: 8 | O3: states | P3: 2 | Q3: 1 | R3: 0 | S3: 0 | T3: 0 | U3: 0 | V3: 0 | W3: 0 | Y3: +2 influence, draw 2 cards, then you may destroy a card in your hand or discard pile. | Z3: discard_leader | AA3: 1 | AB3: The Sedition Act | AC3: The paper (or papers) holding the most offices discards a card at random. | AD3: +2 influence, draw 2 cards, then you may destroy a card in your hand or discard pile. Also +2 of the elected candidate's theme. Worth 3 prestige.
A4: 3 | B4: 1804 | C4: I | D4: The Louisiana Purchase | E4: 3 | F4: 0 | G4: 2 | H4: 2 | I4: Thomas Jefferson | J4: Political | K4: 9 | L4: Charles C. Pinckney | M4: Economic | N4: 11 | O4: nation | P4: 0 | Q4: 0 | R4: 0 | S4: 4 | T4: 0 | U4: 0 | V4: 0 | W4: 0 | Y4: +2 influence. Gain a story costing 4 or less from the exchange. | Z4: draw | AA4: 1 | AB4: The Twelfth Amendment | AC4: Each paper draws a card. | AD4: +2 influence. Gain a story costing 4 or less from the exchange. Also +2 of the elected candidate's theme. Worth 3 prestige.
A5: 4 | B5: 1808 | C5: I | D5: The Embargo | E5: 3 | F5: 0 | G5: 4 | H5: 2 | I5: James Madison | J5: Political | K5: 9 | L5: Charles C. Pinckney | M5: Economic | N5: 11 | O5: nation | P5: 0 | Q5: 0 | R5: 0 | S5: 0 | T5: 0 | U5: 0 | V5: 0 | W5: 0 | Y5: +4 influence. | Z5: discard_dearest | AA5: 1 | AB5: The Embargo | AC5: Each paper discards the most expensive card in its hand. | AD5: +4 influence. Also +2 of the elected candidate's theme. Worth 3 prestige.
A6: 5 | B6: 1812 | C6: I | D6: Mr. Madison's War | E6: 4 | F6: 0 | G6: 0 | H6: 2 | I6: James Madison | J6: Social | K6: 10 | L6: DeWitt Clinton | M6: Political | N6: 12 | O6: nation | P6: 0 | Q6: 0 | R6: 0 | S6: 0 | T6: 0 | U6: 1 | V6: 0 | W6: 0 | Y6: +1 influence for each different kind of card you play this turn. | Z6: scandal_leader | AA6: 1 | AB6: Impressment | AC6: The paper (or papers) with the most prestige gains a Scandal. | AD6: +1 influence for each different kind of card you play this turn. Also +2 of the elected candidate's theme. Worth 4 prestige.
A7: 6 | B7: 1816 | C7: I | D7: Good Feelings | E7: 4 | F7: 0 | G7: 0 | H7: 2 | I7: James Monroe | J7: Economic | K7: 10 | L7: Rufus King | M7: Social | N7: 12 | O7: nation | P7: 3 | Q7: 0 | R7: 0 | S7: 0 | T7: 0 | U7: 0 | V7: 0 | W7: 0 | Y7: Draw 3 cards. | Z7: unscandal | AA7: 1 | AB7: Good Feelings | AC7: Each paper destroys a Scandal in its hand or discard pile. | AD7: Draw 3 cards. Also +2 of the elected candidate's theme. Worth 4 prestige.
A8: 7 | B8: 1820 | C8: II | D8: The Missouri Compromise | E8: 4 | F8: 0 | G8: 0 | H8: 3 | I8: John Quincy Adams | J8: Social | K8: 13 | L8: James Monroe | M8: Political | N8: 11 | O8: states | P8: 0 | Q8: 2 | R8: 1 | S8: 0 | T8: 0 | U8: 0 | V8: 0 | W8: 0 | Y8: Destroy up to 2 cards in your hand or discard pile; draw a card for each. | Z8: discard_leader | AA8: 1 | AB8: A Fire Bell in the Night | AC8: The paper (or papers) holding the most offices discards a card at random. | AD8: Destroy up to 2 cards in your hand or discard pile; draw a card for each. Also +3 of the elected candidate's theme. Worth 4 prestige.
A9: 8 | B9: 1824 | C9: II | D9: The Corrupt Bargain | E9: 4 | F9: 0 | G9: 0 | H9: 3 | I9: John Quincy Adams | J9: Social | K9: 11 | L9: Andrew Jackson | M9: Political | N9: 13 | O9: nation | P9: 0 | Q9: 0 | R9: 0 | S9: 0 | T9: 2 | U9: 0 | V9: 0 | W9: 0 | Y9: Put up to 2 cards from your discard pile into your hand. | Z9: scandal_leader | AA9: 1 | AB9: The Corrupt Bargain | AC9: The paper (or papers) with the most prestige gains a Scandal. | AD9: Put up to 2 cards from your discard pile into your hand. Also +3 of the elected candidate's theme. Worth 4 prestige.
A10: 9 | B10: 1828 | C10: II | D10: The Tariff of Abominations | E10: 5 | F10: 0 | G10: 3 | H10: 3 | I10: John Quincy Adams | J10: Economic | K10: 14 | L10: Andrew Jackson | M10: Social | N10: 12 | O10: states | P10: 1 | Q10: 0 | R10: 0 | S10: 0 | T10: 0 | U10: 0 | V10: 0 | W10: 0 | Y10: +3 influence, draw a card. | Z10: scandal_leader | AA10: 1 | AB10: Mudslinging | AC10: The paper (or papers) with the most prestige gains a Scandal. | AD10: +3 influence, draw a card. Also +3 of the elected candidate's theme. Worth 5 prestige.
A11: 10 | B11: 1832 | C11: II | D11: The Bank War | E11: 5 | F11: 0 | G11: 0 | H11: 3 | I11: Henry Clay | J11: Economic | K11: 14 | L11: Andrew Jackson | M11: Social | N11: 12 | O11: states | P11: 1 | Q11: 0 | R11: 0 | S11: 6 | T11: 0 | U11: 0 | V11: 0 | W11: 0 | Y11: Gain a story costing 6 or less from the exchange. Draw a card. | Z11: sweep | AA11: 1 | AB11: The Veto | AC11: The exchange is swept and dealt afresh. | AD11: Gain a story costing 6 or less from the exchange. Draw a card. Also +3 of the elected candidate's theme. Worth 5 prestige.
A12: 11 | B12: 1836 | C12: II | D12: The Specie Circular | E12: 5 | F12: 0 | G12: 3 | H12: 3 | I12: William Henry Harrison | J12: Political | K12: 15 | L12: Martin Van Buren | M12: Economic | N12: 13 | O12: states | P12: 2 | Q12: 0 | R12: 0 | S12: 0 | T12: 0 | U12: 0 | V12: 0 | W12: 0 | Y12: +3 influence, draw 2 cards. | Z12: discard_leader | AA12: 2 | AB12: The Panic of 1837 | AC12: The paper (or papers) holding the most offices discards 2 cards at random. | AD12: +3 influence, draw 2 cards. Also +3 of the elected candidate's theme. Worth 5 prestige.
A13: 12 | B13: 1840 | C13: II | D13: Log Cabin and Hard Cider | E13: 5 | F13: 0 | G13: 4 | H13: 3 | I13: William Henry Harrison | J13: Social | K13: 13 | L13: Martin Van Buren | M13: Economic | N13: 15 | O13: nation | P13: 0 | Q13: 0 | R13: 0 | S13: 0 | T13: 0 | U13: 0 | V13: 0 | W13: 0 | Y13: +4 influence. | Z13: draw | AA13: 1 | AB13: Tippecanoe and Tyler Too | AC13: Each paper draws a card. | AD13: +4 influence. Also +3 of the elected candidate's theme. Worth 5 prestige.
A14: 13 | B14: 1844 | C14: III | D14: Manifest Destiny | E14: 6 | F14: 0 | G14: 2 | H14: 4 | I14: Henry Clay | J14: Economic | K14: 16 | L14: James K. Polk | M14: Social | N14: 14 | O14: states | P14: 0 | Q14: 0 | R14: 0 | S14: 0 | T14: 0 | U14: 0 | V14: 3 | W14: 0 | Y14: +2 influence. Look at the top 3 stories of the main deck; put one into your hand, the rest on the bottom. | Z14: draw_fewest | AA14: 2 | AB14: Fifty-four Forty | AC14: The paper (or papers) with the fewest offices draws 2 cards. | AD14: +2 influence. Look at the top 3 stories of the main deck; put one into your hand, the rest on the bottom. Also +4 of the elected candidate's theme. Worth 6 prestige.
... A16: 15 | B16: 1852 | C16: III | D16: The Compromise of 1850 | E16: 6 | F16: 0 | G16: 0 | H16: 4 | I16: Winfield Scott | J16: Political | K16: 17 | L16: Franklin Pierce | M16: Economic | N16: 15 | O16: states | P16: 0 | Q16: 3 | R16: 1 | S16: 0 | T16: 0 | U16: 0 | V16: 0 | W16: 0 | Y16: Destroy up to 3 cards in your hand or discard pile; draw a card for each. | Z16: scandal_leader | AA16: 1 | AB16: The Fugitive Slave Act | AC16: The paper (or papers) with the most prestige gains a Scandal. | AD16: Destroy up to 3 cards in your hand or discard pile; draw a card for each. Also +4 of the elected candidate's theme. Worth 6 prestige.
A17: 16 | B17: 1856 | C17: III | D17: Bleeding Kansas | E17: 6 | F17: 0 | G17: 5 | H17: 4 | I17: John C. Fremont | J17: Economic | K17: 17 | L17: James Buchanan | M17: Political | N17: 15 | O17: states | P17: 0 | Q17: 0 | R17: 0 | S17: 0 | T17: 0 | U17: 0 | V17: 0 | W17: 0 | X17: scandal | Y17: +5 influence. Attack: each rival paper gains a Scandal. | Z17: discard_leader | AA17: 2 | AB17: Bleeding Kansas | AC17: The paper (or papers) holding the most offices discards 2 cards at random. | AD17: +5 influence. Attack: each rival paper gains a Scandal. Also +4 of the elected candidate's theme. Worth 6 prestige.
A18: 17 | B18: 1860 | C18: III | D18: Secession Winter | E18: 0 | F18: 1 | G18: 0 | H18: 4 | I18: Abraham Lincoln | J18: Political | K18: 16 | L18: Stephen A. Douglas | M18: Economic | N18: 18 | O18: nation | P18: 0 | Q18: 0 | R18: 0 | S18: 0 | T18: 0 | U18: 0 | V18: 0 | W18: 0 | Y18: The last election: the game ends after this turn. Worth 1 prestige for each election card you hold, this one included. | Z18: destroy_cheapest | AA18: 1 | AB18: Secession | AC18: Each paper destroys the cheapest card in its hand. | AD18: The last election: the game ends after this turn. Worth 1 prestige for each election card you hold, this one included.

Sheet Newspapers
A1: key | B1: name | C1: dc_super_hero | D1: leans | E1: ability | F1: flavor
A2: globe | B2: The Washington Globe | C2: Hawkman | D2: Political | E2: Your Political influence counts toward any candidate. | F2: Francis Blair's Globe, the party organ of the Jackson men: the line came from the White House.
A3: argus | B3: The Albany Argus | C3: Red Tornado | D3: Political | E3: Each election you win is worth +1 prestige at the end of the game. | F3: The voice of the Albany Regency, Van Buren's machine. It could elect anyone the party named.
A4: intelligencer | B4: The National Intelligencer | C4: Booster Gold | D4: Political | E4: You never gain Scandals: when a negative story would give you one, ignore it. | F4: Gales and Seaton's paper of record, printing the debates of Congress. Too dull to smear.
A5: journal | B5: The Journal of Commerce | C5: Nightwing | D5: Economic | E5: Your first and second Economic stories each turn give +1 influence each. | F5: Prices current, ship arrivals and the money market, for the merchants of New York.
A6: herald | B6: The New York Herald | C6: Shazam! | D6: Economic | E6: Once each turn, you may pay 2 influence to set aside the top story of the main deck; it joins your next hand. | F6: James Gordon Bennett's Herald: first with the news, by any means, at any cost.
A7: sun | B7: The Sun | C7: Batgirl | D7: Social | E7: Once each turn, you may discard a Scandal from your hand to draw three cards. | F7: Benjamin Day's Sun, a penny a copy: police court, murders, and the moon men.
A8: north_star | B8: The North Star | C8: Starfire | D8: Social | E8: Once each turn, if you play two or more Social stories, draw a card. | F8: Frederick Douglass's weekly from Rochester: "Right is of no sex - Truth is of no color."
A9: aurora | B9: The Aurora | C9: Black Canary | D9: Negative | E9: +1 influence for each different negative story you play. | F9: Benjamin Franklin Bache's Aurora, which called Washington a tyrant and Adams worse.

Sheet Summary
A1: Summary of the Stories sheet (formulas: edit the Stories sheet and these update)
A3: Card type | B3: Kinds | C3: Copies | D3: Total prestige (vp x copies)
A4: Political story | B4: =COUNTIFS(Stories!$C$2:$C$111,$A4) | C4: =SUMIFS(Stories!$AA$2:$AA$111,Stories!$C$2:$C$111,$A4) | D4: =SUMPRODUCT((Stories!$C$2:$C$111=$A4)*Stories!$F$2:$F$111*Stories!$AA$2:$AA$111)
A5: Economic story | B5: =COUNTIFS(Stories!$C$2:$C$111,$A5) | C5: =SUMIFS(Stories!$AA$2:$AA$111,Stories!$C$2:$C$111,$A5) | D5: =SUMPRODUCT((Stories!$C$2:$C$111=$A5)*Stories!$F$2:$F$111*Stories!$AA$2:$AA$111)
A6: Social story | B6: =COUNTIFS(Stories!$C$2:$C$111,$A6) | C6: =SUMIFS(Stories!$AA$2:$AA$111,Stories!$C$2:$C$111,$A6) | D6: =SUMPRODUCT((Stories!$C$2:$C$111=$A6)*Stories!$F$2:$F$111*Stories!$AA$2:$AA$111)
A7: Negative story | B7: =COUNTIFS(Stories!$C$2:$C$111,$A7) | C7: =SUMIFS(Stories!$AA$2:$AA$111,Stories!$C$2:$C$111,$A7) | D7: =SUMPRODUCT((Stories!$C$2:$C$111=$A7)*Stories!$F$2:$F$111*Stories!$AA$2:$AA$111)
A8: Media event | B8: =COUNTIFS(Stories!$C$2:$C$111,$A8) | C8: =SUMIFS(Stories!$AA$2:$AA$111,Stories!$C$2:$C$111,$A8) | D8: =SUMPRODUCT((Stories!$C$2:$C$111=$A8)*Stories!$F$2:$F$111*Stories!$AA$2:$AA$111)
A9: Starter | B9: =COUNTIFS(Stories!$C$2:$C$111,$A9) | C9: =SUMIFS(Stories!$AA$2:$AA$111,Stories!$C$2:$C$111,$A9) | D9: =SUMPRODUCT((Stories!$C$2:$C$111=$A9)*Stories!$F$2:$F$111*Stories!$AA$2:$AA$111)
A10: Editorial | B10: =COUNTIFS(Stories!$C$2:$C$111,$A10) | C10: =SUMIFS(Stories!$AA$2:$AA$111,Stories!$C$2:$C$111,$A10) | D10: =SUMPRODUCT((Stories!$C$2:$C$111=$A10)*Stories!$F$2:$F$111*Stories!$AA$2:$AA$111)
A11: Scandal | B11: =COUNTIFS(Stories!$C$2:$C$111,$A11) | C11: =SUMIFS(Stories!$AA$2:$AA$111,Stories!$C$2:$C$111,$A11) | D11: =SUMPRODUCT((Stories!$C$2:$C$111=$A11)*Stories!$F$2:$F$111*Stories!$AA$2:$AA$111)
A12: Total | B12: =SUM(B4:B11) | C12: =SUM(C4:C11) | D12: =SUM(D4:D11)
A14: Theme (stories and negative stories) | B14: Era I | C14: Era II | D14: Era III | E14: All
A15: Political | B15: =COUNTIFS(Stories!$D$2:$D$111,$A15,Stories!$Y$2:$Y$111,">=1796",Stories!$Y$2:$Y$111,"<=1804") | C15: =COUNTIFS(Stories!$D$2:$D$111,$A15,Stories!$Y$2:$Y$111,">=1808",Stories!$Y$2:$Y$111,"<=1828") | D15: =COUNTIFS(Stories!$D$2:$D$111,$A15,Stories!$Y$2:$Y$111,">=1832",Stories!$Y$2:$Y$111,"<=1860") | E15: =SUM(B15:D15)
A16: Economic | B16: =COUNTIFS(Stories!$D$2:$D$111,$A16,Stories!$Y$2:$Y$111,">=1796",Stories!$Y$2:$Y$111,"<=1804") | C16: =COUNTIFS(Stories!$D$2:$D$111,$A16,Stories!$Y$2:$Y$111,">=1808",Stories!$Y$2:$Y$111,"<=1828") | D16: =COUNTIFS(Stories!$D$2:$D$111,$A16,Stories!$Y$2:$Y$111,">=1832",Stories!$Y$2:$Y$111,"<=1860") | E16: =SUM(B16:D16)
A17: Social | B17: =COUNTIFS(Stories!$D$2:$D$111,$A17,Stories!$Y$2:$Y$111,">=1796",Stories!$Y$2:$Y$111,"<=1804") | C17: =COUNTIFS(Stories!$D$2:$D$111,$A17,Stories!$Y$2:$Y$111,">=1808",Stories!$Y$2:$Y$111,"<=1828") | D17: =COUNTIFS(Stories!$D$2:$D$111,$A17,Stories!$Y$2:$Y$111,">=1832",Stories!$Y$2:$Y$111,"<=1860") | E17: =SUM(B17:D17)
A19: Elections: fixed prestige on the 17 cards (1860 is worth 1 per office held, not counted) | B19: =SUM(Elections!$E$2:$E$18)
